typedkafka/__init__.py
typedkafka/admin.py
typedkafka/aio.py
typedkafka/config.py
typedkafka/consumer.py
typedkafka/dlq.py
typedkafka/exceptions.py
typedkafka/logging.py
typedkafka/metrics.py
typedkafka/producer.py
typedkafka/protobuf.py
typedkafka/py.typed
typedkafka/retry.py
typedkafka/serializers.py
typedkafka/telemetry.py
typedkafka/testing.py
typedkafka/topics.py
typedkafka-0.7.0.dist-info/METADATA
typedkafka-0.7.0.dist-info/WHEEL
typedkafka-0.7.0.dist-info/licenses/LICENSE
typedkafka-0.7.0.dist-info/RECORD
