Metadata-Version: 2.4
Name: typedkafka
Version: 0.7.0
Summary: A well-documented, fully type-hinted Kafka client for Python
Project-URL: Homepage, https://github.com/Jgprog117/typedkafka
Project-URL: Documentation, https://Jgprog117.github.io/typedkafka
Project-URL: Repository, https://github.com/Jgprog117/typedkafka
Project-URL: Issues, https://github.com/Jgprog117/typedkafka/issues
Author: typedkafka contributors
License: MIT
License-File: LICENSE
Keywords: confluent-kafka,consumer,documentation,event-driven,kafka,messaging,producer,streaming,type-hints,typed
Classifier: Development Status :: 4 - Beta
Classifier: Intended Audience :: Developers
Classifier: License :: OSI Approved :: MIT License
Classifier: Operating System :: OS Independent
Classifier: Programming Language :: Python :: 3
Classifier: Programming Language :: Python :: 3.9
Classifier: Programming Language :: Python :: 3.10
Classifier: Programming Language :: Python :: 3.11
Classifier: Programming Language :: Python :: 3.12
Classifier: Programming Language :: Python :: 3.13
Classifier: Topic :: Software Development :: Libraries :: Python Modules
Classifier: Topic :: System :: Distributed Computing
Classifier: Typing :: Typed
Requires-Python: >=3.9
Requires-Dist: confluent-kafka>=2.0.0
Provides-Extra: all
Requires-Dist: confluent-kafka[avro]>=2.0.0; extra == 'all'
Requires-Dist: confluent-kafka[protobuf]>=2.0.0; extra == 'all'
Requires-Dist: protobuf>=4.0; extra == 'all'
Provides-Extra: avro
Requires-Dist: confluent-kafka[avro]>=2.0.0; extra == 'avro'
Provides-Extra: dev
Requires-Dist: mypy>=1.0.0; extra == 'dev'
Requires-Dist: pytest-asyncio>=0.21.0; extra == 'dev'
Requires-Dist: pytest-cov>=4.0.0; extra == 'dev'
Requires-Dist: pytest>=7.0.0; extra == 'dev'
Requires-Dist: ruff>=0.1.0; extra == 'dev'
Provides-Extra: docs
Requires-Dist: mkdocs-material>=9.0.0; extra == 'docs'
Requires-Dist: mkdocs>=1.5.0; extra == 'docs'
Requires-Dist: mkdocstrings[python]>=0.24.0; extra == 'docs'
Provides-Extra: protobuf
Requires-Dist: confluent-kafka[protobuf]>=2.0.0; extra == 'protobuf'
Requires-Dist: protobuf>=4.0; extra == 'protobuf'
